{"cameraMode":{"drawMode":0,"name":"Shaded","section":"Shading Mode"},"sceneLighting":false,"audioPlay":false,"sceneViewState":{"m_AlwaysRefresh":false,"showFog":true,"showSkybox":false,"showFlares":true,"showImageEffects":true,"showParticleSystems":true,"showVisualEffectGraphs":true,"m_FxEnabled":true},"in2DMode":false,"pivot":{"x":1092.332763671875,"y":556.8959350585938,"z":-55.84055709838867},"rotation":{"x":0.1339602917432785,"y":0.25869205594062807,"z":-0.03622613474726677,"w":0.9559729099273682},"size":1101.45361328125,"orthographic":false}